CHANGELOG.txt
LICENCE.txt
MANIFEST.in
README.txt
setup.py
wordleimageeditor/__init__.py
wordleimageeditor/font.ttf
wordleimageeditor/image_maker.py
wordleimageeditor.egg-info/PKG-INFO
wordleimageeditor.egg-info/SOURCES.txt
wordleimageeditor.egg-info/dependency_links.txt
wordleimageeditor.egg-info/requires.txt
wordleimageeditor.egg-info/top_level.txt
wordleimageeditor/images/green.png
wordleimageeditor/images/grey.png
wordleimageeditor/images/main.png
wordleimageeditor/images/yellow.png