Metadata-Version: 1.1
Name: wordleimageeditor
Version: 0.0.3
Summary: A module for creating images for Wordle
Home-page: UNKNOWN
Author: Artyom Ulyanov
Author-email: uljanoff.artem@yandex.ru
License: MIT
Keywords: wordle
Platform: UNKNOWN
Classifier: Development Status :: 5 - Production/Stable
Classifier: Intended Audience :: Education
Classifier: Operating System :: Microsoft :: Windows :: Windows 10
Classifier: License :: OSI Approved :: MIT License
Classifier: Programming Language :: Python :: 3
